{
  "date": "2026-07-17",
  "top_25_tracks": [
    {
      "artist_name": "Rackelle",
      "artist_uuid": "360690c5-d6f7-46e2-aa98-7ac068ffbcdc",
      "artist_tier": "Tier 2 - Growth/Graduate Watch",
      "artist_spotify_url": "https://open.spotify.com/artist/5RUZSiHlbdwSjfPqfGA036",
      "track_title": "Invincible - VIP Radio Edit",
      "track_spotify_url": "https://open.spotify.com/track/2zPRbCh0weGRkzPHVDLNpH",
      "release_date": "2024-11-19",
      "streams_1d": 3199,
      "streams_1w": 18586,
      "streams_1w_growth": 1858500,
      "streams_1m": 18587,
      "track_score": 345439396.0
    },
    {
      "artist_name": "Lilly Hart",
      "artist_uuid": "b19ef77f-8f85-404d-a0d3-7e093c1c2fe0",
      "artist_tier": "Tier 1 - Developing",
      "artist_spotify_url": "https://open.spotify.com/artist/2Vm9OsgWjGKAvH6Iu5gj5M",
      "track_title": "1-800-KISSME",
      "track_spotify_url": "https://open.spotify.com/track/0hF1Z6RBpLoZRMNaVwAxWo",
      "release_date": "2026-06-05",
      "streams_1d": 0,
      "streams_1w": 87872,
      "streams_1w_growth": 6706.51,
      "streams_1m": 93430,
      "track_score": 5981016.5
    },
    {
      "artist_name": "Fred again..",
      "artist_uuid": "0429fb90-d544-452a-bf54-1ab289b1a678",
      "artist_tier": "watchlist",
      "artist_spotify_url": "https://open.spotify.com/artist/4oLeXFyACqeem2VImYeBFe",
      "track_title": "Marea (We\u2019ve Lost Dancing)",
      "track_spotify_url": "https://open.spotify.com/track/3YDg7ZZQmaO9qOB8psKRt9",
      "release_date": "2021-02-22",
      "streams_1d": 248071,
      "streams_1w": 1827899,
      "streams_1w_growth": 6.54,
      "streams_1m": 7560261,
      "track_score": 1947443.6
    },
    {
      "artist_name": "Fred again..",
      "artist_uuid": "0429fb90-d544-452a-bf54-1ab289b1a678",
      "artist_tier": "watchlist",
      "artist_spotify_url": "https://open.spotify.com/artist/4oLeXFyACqeem2VImYeBFe",
      "track_title": "leavemealone",
      "track_spotify_url": "https://open.spotify.com/track/2h8PCZRGBv7ayMVmWidpvd",
      "release_date": "2022-01-18",
      "streams_1d": 165539,
      "streams_1w": 1178625,
      "streams_1w_growth": -4.79,
      "streams_1m": 5142620,
      "track_score": 1178625.0
    },
    {
      "artist_name": "Fred again..",
      "artist_uuid": "0429fb90-d544-452a-bf54-1ab289b1a678",
      "artist_tier": "watchlist",
      "artist_spotify_url": "https://open.spotify.com/artist/4oLeXFyACqeem2VImYeBFe",
      "track_title": "i adore u",
      "track_spotify_url": "https://open.spotify.com/track/1NwJBJsjbLMd1iLhJG174d",
      "release_date": "2023-08-11",
      "streams_1d": 144652,
      "streams_1w": 1049353,
      "streams_1w_growth": 5.48,
      "streams_1m": 4370553,
      "track_score": 1106857.5
    },
    {
      "artist_name": "Fred again..",
      "artist_uuid": "0429fb90-d544-452a-bf54-1ab289b1a678",
      "artist_tier": "watchlist",
      "artist_spotify_url": "https://open.spotify.com/artist/4oLeXFyACqeem2VImYeBFe",
      "track_title": "Delilah (pull me out of this)",
      "track_spotify_url": "https://open.spotify.com/track/112IbkdGRZ6oWlTuA1cLoe",
      "release_date": "2022-10-17",
      "streams_1d": 148598,
      "streams_1w": 1083828,
      "streams_1w_growth": -1.34,
      "streams_1m": 4774382,
      "track_score": 1083828.0
    },
    {
      "artist_name": "Fred again..",
      "artist_uuid": "0429fb90-d544-452a-bf54-1ab289b1a678",
      "artist_tier": "watchlist",
      "artist_spotify_url": "https://open.spotify.com/artist/4oLeXFyACqeem2VImYeBFe",
      "track_title": "Turn On The Lights again.. (feat. Future)",
      "track_spotify_url": "https://open.spotify.com/track/6jJlkCpr5ztFNIhEUWbMrE",
      "release_date": "2022-01-17",
      "streams_1d": 78955,
      "streams_1w": 552481,
      "streams_1w_growth": -0.91,
      "streams_1m": 2395710,
      "track_score": 552481.0
    },
    {
      "artist_name": "andrew reed & the liberation",
      "artist_uuid": "cff6f1a5-11cc-4ff7-be89-e22e51ab0c6b",
      "artist_tier": "Tier 0 - Emerging",
      "artist_spotify_url": "https://open.spotify.com/artist/2Lx7DnbB5qyt7uwV8yeHwE",
      "track_title": "Thunder in My Soul (Radio Edit)",
      "track_spotify_url": "https://open.spotify.com/track/7woWsiJLrq12SPUOoKDbzN",
      "release_date": "2025-06-06",
      "streams_1d": 955,
      "streams_1w": 3309,
      "streams_1w_growth": 5705.26,
      "streams_1m": 3544,
      "track_score": 192096.1
    },
    {
      "artist_name": "Faith Leazae",
      "artist_uuid": "f9c0d609-8d6a-43ec-a2bf-db625a89ddfb",
      "artist_tier": "watchlist",
      "artist_spotify_url": "https://open.spotify.com/artist/4TxDGE47ujPYGydYcr7DEM",
      "track_title": "Gimme a Gas Station?",
      "track_spotify_url": "https://open.spotify.com/track/6wAIG7KGLnMGk7wVf7F3RB",
      "release_date": "2026-04-24",
      "streams_1d": 0,
      "streams_1w": 81014,
      "streams_1w_growth": -24.11,
      "streams_1m": 492351,
      "track_score": 81014.0
    },
    {
      "artist_name": "Arkow",
      "artist_uuid": "1bc44f64-620e-4365-9ce9-1f19ad17a3d5",
      "artist_tier": "Tier 1 - Developing",
      "artist_spotify_url": "https://open.spotify.com/artist/7jLjtOZxfJaNvI57ugy2sk",
      "track_title": "Mind the Gap",
      "track_spotify_url": "https://open.spotify.com/track/53iMlq17Mybuy7ZmkCw7lY",
      "release_date": "2026-06-15",
      "streams_1d": 0,
      "streams_1w": 51522,
      "streams_1w_growth": -36.09,
      "streams_1m": 417052,
      "track_score": 51522.0
    },
    {
      "artist_name": "Nirosta Steel",
      "artist_uuid": "c3625737-2597-4090-924a-d898112ff819",
      "artist_tier": "watchlist",
      "artist_spotify_url": "https://open.spotify.com/artist/6B6MO6Q4QoLGVq7Kf8vlGM",
      "track_title": "ENGLISH PARTY",
      "track_spotify_url": "https://open.spotify.com/track/70hWEnSlRAI5ibDlB8LI8Q",
      "release_date": "2026-06-29",
      "streams_1d": 0,
      "streams_1w": 41826,
      "streams_1w_growth": null,
      "streams_1m": 49208,
      "track_score": 41826.0
    },
    {
      "artist_name": "Nirosta Steel",
      "artist_uuid": "c3625737-2597-4090-924a-d898112ff819",
      "artist_tier": "watchlist",
      "artist_spotify_url": "https://open.spotify.com/artist/6B6MO6Q4QoLGVq7Kf8vlGM",
      "track_title": "BOSS TRIX (BENNY'S SONG)",
      "track_spotify_url": "https://open.spotify.com/track/46pgwcM7CdrraI1FXZE1FY",
      "release_date": "2026-05-01",
      "streams_1d": 0,
      "streams_1w": 41679,
      "streams_1w_growth": null,
      "streams_1m": 47920,
      "track_score": 41679.0
    },
    {
      "artist_name": "Mattie Pruitt",
      "artist_uuid": "7cd461a8-6344-479e-ae82-97edc7068cd4",
      "artist_tier": "Tier 2 - Growth/Graduate Watch",
      "artist_spotify_url": "https://open.spotify.com/artist/0RpLfoG8oYbdNAAxlr0mWb",
      "track_title": "Like Me",
      "track_spotify_url": "https://open.spotify.com/track/4BduDuBdTaiMZEqx3Ac19r",
      "release_date": "2026-07-10",
      "streams_1d": 0,
      "streams_1w": 37891,
      "streams_1w_growth": null,
      "streams_1m": 37891,
      "track_score": 37891.0
    },
    {
      "artist_name": "MyGuyMars",
      "artist_uuid": "1f391126-c982-4212-b960-f251a7c7f48b",
      "artist_tier": "Tier 2 - Growth/Graduate Watch",
      "artist_spotify_url": "https://open.spotify.com/artist/0oH03sDsnxkWo7jFl6nZQ6",
      "track_title": "Me Tripeo",
      "track_spotify_url": "https://open.spotify.com/track/4EGBRD3K4yfA1prw06QhFt",
      "release_date": "2026-02-14",
      "streams_1d": 2958,
      "streams_1w": 19389,
      "streams_1w_growth": 81.53,
      "streams_1m": 59367,
      "track_score": 35196.9
    },
    {
      "artist_name": "Stolen Valor",
      "artist_uuid": "10efab0c-2d64-47a5-88a3-56e1ce88a386",
      "artist_tier": "Tier 2 - Growth/Graduate Watch",
      "artist_spotify_url": "https://open.spotify.com/artist/74RuyNcMXz3vdn6feUkp6Y",
      "track_title": "Where I Belong",
      "track_spotify_url": "https://open.spotify.com/track/5k0fSThrAcGwBhxZz91wdp",
      "release_date": "2026-07-10",
      "streams_1d": 0,
      "streams_1w": 34876,
      "streams_1w_growth": null,
      "streams_1m": 34876,
      "track_score": 34876.0
    },
    {
      "artist_name": "Braedon Barnhill",
      "artist_uuid": "8377aefb-86b9-49e7-8deb-3539d6b54fa4",
      "artist_tier": "Tier 2 - Growth/Graduate Watch",
      "artist_spotify_url": "https://open.spotify.com/artist/6havQH2xpTlwoGLDDTgd49",
      "track_title": "Long Way to Lubbock",
      "track_spotify_url": "https://open.spotify.com/track/7uSLf2Z33IJa7Fv1psFXNN",
      "release_date": "2026-07-03",
      "streams_1d": 0,
      "streams_1w": 33993,
      "streams_1w_growth": null,
      "streams_1m": 43628,
      "track_score": 33993.0
    },
    {
      "artist_name": "Arkow",
      "artist_uuid": "1bc44f64-620e-4365-9ce9-1f19ad17a3d5",
      "artist_tier": "Tier 1 - Developing",
      "artist_spotify_url": "https://open.spotify.com/artist/7jLjtOZxfJaNvI57ugy2sk",
      "track_title": "I Should've Called",
      "track_spotify_url": "https://open.spotify.com/track/2A55hUXVeFtzyCUu7T8toy",
      "release_date": "2026-07-07",
      "streams_1d": 0,
      "streams_1w": 31402,
      "streams_1w_growth": null,
      "streams_1m": 39563,
      "track_score": 31402.0
    },
    {
      "artist_name": "Nirosta Steel",
      "artist_uuid": "c3625737-2597-4090-924a-d898112ff819",
      "artist_tier": "watchlist",
      "artist_spotify_url": "https://open.spotify.com/artist/6B6MO6Q4QoLGVq7Kf8vlGM",
      "track_title": "NEW BOY",
      "track_spotify_url": "https://open.spotify.com/track/5eooxuz7s3uZAdLt739RRs",
      "release_date": "2026-06-29",
      "streams_1d": 0,
      "streams_1w": 27649,
      "streams_1w_growth": null,
      "streams_1m": 31806,
      "track_score": 27649.0
    },
    {
      "artist_name": "Eve Lauren",
      "artist_uuid": "d9b07a19-d0e8-48d5-baf7-b8c5cfa588f2",
      "artist_tier": "Tier 2 - Growth/Graduate Watch",
      "artist_spotify_url": "https://open.spotify.com/artist/0VGRIovFmOFenDy7hnwr7g",
      "track_title": "Kick Back",
      "track_spotify_url": "https://open.spotify.com/track/3PLXh3XJRYXmKRsbmONqDd",
      "release_date": "2026-07-10",
      "streams_1d": 0,
      "streams_1w": 25353,
      "streams_1w_growth": null,
      "streams_1m": 25353,
      "track_score": 25353.0
    },
    {
      "artist_name": "Nirosta Steel",
      "artist_uuid": "c3625737-2597-4090-924a-d898112ff819",
      "artist_tier": "watchlist",
      "artist_spotify_url": "https://open.spotify.com/artist/6B6MO6Q4QoLGVq7Kf8vlGM",
      "track_title": "YHEMA",
      "track_spotify_url": "https://open.spotify.com/track/3QlsjEr2r82hlMB2IxNjs7",
      "release_date": "2026-05-01",
      "streams_1d": 0,
      "streams_1w": 23912,
      "streams_1w_growth": null,
      "streams_1m": 27468,
      "track_score": 23912.0
    },
    {
      "artist_name": "Nirosta Steel",
      "artist_uuid": "c3625737-2597-4090-924a-d898112ff819",
      "artist_tier": "watchlist",
      "artist_spotify_url": "https://open.spotify.com/artist/6B6MO6Q4QoLGVq7Kf8vlGM",
      "track_title": "MY NAME IS NIGHT",
      "track_spotify_url": "https://open.spotify.com/track/63u2WKz7Dobbr1zfipD8eg",
      "release_date": "2026-06-12",
      "streams_1d": 0,
      "streams_1w": 21655,
      "streams_1w_growth": null,
      "streams_1m": 25295,
      "track_score": 21655.0
    },
    {
      "artist_name": "Dayshawnx",
      "artist_uuid": "6c900f33-3c10-4021-ae32-4ccc50eadf9a",
      "artist_tier": "Tier 1 - Developing",
      "artist_spotify_url": "https://open.spotify.com/artist/6oHEIVKrKPFauVjhUV700d",
      "track_title": "NO FEELING LASTS FOREVER",
      "track_spotify_url": "https://open.spotify.com/track/3sXLFk2a7G9ZYlhP1RzxV4",
      "release_date": "2026-07-10",
      "streams_1d": 0,
      "streams_1w": 21282,
      "streams_1w_growth": null,
      "streams_1m": 21282,
      "track_score": 21282.0
    },
    {
      "artist_name": "Sophia Sugarman",
      "artist_uuid": "f09fd826-8e74-42b6-bc1f-bb35e6892607",
      "artist_tier": "Tier 2 - Growth/Graduate Watch",
      "artist_spotify_url": "https://open.spotify.com/artist/4FMHVCDosmwVWwsMsSdBPz",
      "track_title": "Magic Place",
      "track_spotify_url": "https://open.spotify.com/track/3YLWmGMCZ8JfG0diBVC0vf",
      "release_date": "2026-07-10",
      "streams_1d": 0,
      "streams_1w": 19016,
      "streams_1w_growth": null,
      "streams_1m": 19016,
      "track_score": 19016.0
    },
    {
      "artist_name": "Morgan Guerin",
      "artist_uuid": "d62bc11a-1ec3-4664-ba0f-97eebf51ea13",
      "artist_tier": "Tier 0 - Emerging",
      "artist_spotify_url": "https://open.spotify.com/artist/17j0vWqj5tc8GO1U3izp8d",
      "track_title": "Solidarity Song",
      "track_spotify_url": "https://open.spotify.com/track/2EUuB8eqBKC9FHDI5ZMESQ",
      "release_date": "2026-06-19",
      "streams_1d": 0,
      "streams_1w": 17705,
      "streams_1w_growth": -23.12,
      "streams_1m": 87943,
      "track_score": 17705.0
    },
    {
      "artist_name": "Markis Precise",
      "artist_uuid": "661868b6-bae1-4060-a7d7-3247425b70eb",
      "artist_tier": "Tier 1 - Developing",
      "artist_spotify_url": "https://open.spotify.com/artist/2diXgS9TzzzDVmAgBiACRM",
      "track_title": "Sweet Stuff",
      "track_spotify_url": "https://open.spotify.com/track/3P8Psm5M7rOjWDhHbeAOZH",
      "release_date": "2021-08-27",
      "streams_1d": 121,
      "streams_1w": 2437,
      "streams_1w_growth": 623.15,
      "streams_1m": 3521,
      "track_score": 17623.2
    }
  ]
}